pyadps/Home_Page.py
pyadps/__init__.py
pyadps/__main__.py
pyadps/pages/01_Read_File.py
pyadps/pages/02_View_Raw_Data.py
pyadps/pages/03_Download_Raw_File.py
pyadps/pages/04_Sensor_Health.py
pyadps/pages/05_QC_Test.py
pyadps/pages/06_Profile_Test.py
pyadps/pages/07_Velocity_Test.py
pyadps/pages/08_Write_File.py
pyadps/pages/09_Add-Ons.py
pyadps/pages/__init__.py
pyadps/utils/__init__.py
pyadps/utils/autoprocess.py
pyadps/utils/logging_utils.py
pyadps/utils/metadata/config.ini
pyadps/utils/metadata/demo.000
pyadps/utils/metadata/flmeta.json
pyadps/utils/metadata/vlmeta.json
pyadps/utils/multifile.py
pyadps/utils/plotgen.py
pyadps/utils/profile_test.py
pyadps/utils/pyreadrdi.py
pyadps/utils/readrdi.py
pyadps/utils/script.py
pyadps/utils/sensor_health.py
pyadps/utils/signal_quality.py
pyadps/utils/velocity_test.py
pyadps/utils/writenc.py
pyadps-0.3.3.dist-info/LICENSE
pyadps-0.3.3.dist-info/METADATA
pyadps-0.3.3.dist-info/WHEEL
pyadps-0.3.3.dist-info/entry_points.txt
pyadps-0.3.3.dist-info/RECORD
