Metadata-Version: 2.3
Name: pyadps
Version: 0.3.3
Summary: A Python package for ADCP data processing
License: MIT
Keywords: adcp,data-processing,oceanography
Author: P. Amol
Author-email: prakashamol@gmail.com
Requires-Python: >=3.12,<4.0.0
Classifier: License :: OSI Approved :: MIT License
Classifier: Operating System :: OS Independent
Classifier: Programming Language :: Python :: 3
Classifier: Programming Language :: Python :: 3.12
Classifier: Programming Language :: Python :: 3.13
Requires-Dist: cmake (>=3.30.2)
Requires-Dist: matplotlib (>=3.8.4,<3.9.0)
Requires-Dist: meson (>=1.4.1)
Requires-Dist: netCDF4 (>=1.7.1,<1.8.0)
Requires-Dist: numpy (>=1.26.4,<1.27.0)
Requires-Dist: pandas (>=2.2.2,<2.3.0)
Requires-Dist: plotly (>=5.22.0,<5.23.0)
Requires-Dist: plotly-resampler (>=0.10.0,<0.11.0)
Requires-Dist: pygeomag (>=1.1.0,<2.0.0)
Requires-Dist: scipy (>=1.14.0,<1.15.0)
Requires-Dist: streamlit (>=1.36.0,<1.37.0)
Project-URL: Documentation, https://pyadps.readthedocs.io/en/latest/index.html
Project-URL: Repository, https://github.com/p-amol/pyadps
Project-URL: homepage, https://pyadps.readthedocs.io/en/latest/index.html
